[
    {
        "nom": "AdaLovelace",
        "imatge": "assets/AdaLovelace.jpg",
        "biografies": {
            "biografiaCat": "Aquí tenim la biografia en català",
            "biografiaCast": "Aquí tenim la biografia en castellà",
            "biografiaAng": "Aquí tenim la biografia en anglès"
        },
        "position_x": -14.8,
        "position_y": 2,
        "position_z": -5,
        "depth": 5,
        "width": 0.1,
        "height": 7,
        "alert": "holita"
    },
    {
        "nom": "HedyLamarr",
        "imatge": "assets/HedyLamarr.jpg",
        "biografies": {
            "biografiaCat": "Aquí tenim la biografia en català",
            "biografiaCast": "Aquí tenim la biografia en castellà",
            "biografiaAng": "Aquí tenim la biografia en anglès"
        },
        "position_x": -14.8,
        "position_y": 2,
        "position_z": -15,
        "depth": 5,
        "width": 0.2,
        "height": 7,
        "alert": "holita"
    },
    {
        "nom": "HedyLamarr2",
        "imatge": "assets/HedyLamarr.jpg",
        "biografies": {
            "biografiaCat": "Aquí tenim la biografia en català",
            "biografiaCast": "Aquí tenim la biografia en castellà",
            "biografiaAng": "Aquí tenim la biografia en anglès"
        },
        "position_x": -14.8,
        "position_y": 2,
        "position_z": -25,
        "depth": 5,
        "width": 0.2,
        "height": 7,
        "alert": "holita"
    }
]